clock_cli/__init__.py
clock_cli-0.1.4.dist-info/entry_points.txt
clock_cli-0.1.4.dist-info/WHEEL
clock_cli-0.1.4.dist-info/METADATA
clock_cli-0.1.4.dist-info/RECORD
